mdnotes/__init__.py
mdnotes/api_helper.py
mdnotes/configuration.py
mdnotes/decorators.py
mdnotes/mdnotes_client.py
mdnotes/controllers/__init__.py
mdnotes/controllers/base_controller.py
mdnotes/controllers/service_controller.py
mdnotes/controllers/user_controller.py
mdnotes/exceptions/__init__.py
mdnotes/exceptions/api_exception.py
mdnotes/exceptions/o_auth_provider_exception.py
mdnotes/http/__init__.py
mdnotes/http/http_call_back.py
mdnotes/http/http_client.py
mdnotes/http/http_method_enum.py
mdnotes/http/http_request.py
mdnotes/http/http_response.py
mdnotes/http/requests_client.py
mdnotes/models/__init__.py
mdnotes/models/note.py
mdnotes/models/o_auth_provider_error_enum.py
mdnotes/models/o_auth_token.py
mdnotes/models/service_status.py
mdnotes/models/user.py
mdnotes/utilities/__init__.py
mdnotes/utilities/file_wrapper.py
Md_Notes_api-1.0.0.dist-info/LICENSE
Md_Notes_api-1.0.0.dist-info/METADATA
Md_Notes_api-1.0.0.dist-info/WHEEL
Md_Notes_api-1.0.0.dist-info/top_level.txt
Md_Notes_api-1.0.0.dist-info/RECORD
